ubigeoai/AIGeoUbi.py
ubigeoai/__init__.py
ubigeoaii-0.2.3.dist-info/LICENSE.txt
ubigeoaii-0.2.3.dist-info/METADATA
ubigeoaii-0.2.3.dist-info/WHEEL
ubigeoaii-0.2.3.dist-info/top_level.txt
ubigeoaii-0.2.3.dist-info/RECORD
