Metadata-Version: 2.1
Name: ubigeoaii
Version: 0.2.3
Summary: Libreria que automatiza procesos espaciales complejos
Home-page: https://github.com/brayancarichi/UbiGeoAI.git
Author: GEOINFORMATICA UACJ
Author-email: brayanmurillogutierrez988@outlook.es
License-File: LICENSE.txt
Requires-Dist: fastai
Requires-Dist: geopandas
Requires-Dist: imutils
Requires-Dist: ipython
Requires-Dist: matplotlib
Requires-Dist: numpy
Requires-Dist: opencv-python
Requires-Dist: opencv-python-headless
Requires-Dist: pandas
Requires-Dist: Pillow
Requires-Dist: rasterio
Requires-Dist: scikit-learn
Requires-Dist: seaborn
Requires-Dist: Shapely
Requires-Dist: scikit-image
Requires-Dist: supervision
Requires-Dist: tqdm
Requires-Dist: ultralytics
Requires-Dist: requests
Requires-Dist: fiona
